vespa/__init__.py
vespa/check_dependencies.py
vespa/create_shortcuts.py
vespa/requirements.txt
vespa/analysis/__init__.py
vespa/analysis/block.py
vespa/analysis/block_fit_giso.py
vespa/analysis/block_fit_giso_Last.py
vespa/analysis/block_fit_identity.py
vespa/analysis/block_fit_voigt - Copy.py
vespa/analysis/block_fit_voigt.py
vespa/analysis/block_prep_edit_fidsum.py
vespa/analysis/block_prep_fidsum.py
vespa/analysis/block_prep_identity.py
vespa/analysis/block_prep_megalaser.py
vespa/analysis/block_prep_timeseries.py
vespa/analysis/block_prep_wbnaa.py
vespa/analysis/block_quant_identity.py
vespa/analysis/block_quant_watref.py
vespa/analysis/block_raw.py
vespa/analysis/block_raw_cmrr_slaser.py
vespa/analysis/block_raw_edit.py
vespa/analysis/block_raw_edit_fidsum.py
vespa/analysis/block_raw_probep.py
vespa/analysis/block_spectral.py
vespa/analysis/block_spectral_identity.py
vespa/analysis/chain_base.py
vespa/analysis/chain_fit_giso.py
vespa/analysis/chain_fit_identity.py
vespa/analysis/chain_fit_voigt.py
vespa/analysis/chain_prep_fidsum.py
vespa/analysis/chain_prep_identity.py
vespa/analysis/chain_prep_megalaser.py
vespa/analysis/chain_prep_timeseries.py
vespa/analysis/chain_prep_wbnaa.py
vespa/analysis/chain_quant_identity.py
vespa/analysis/chain_quant_watref.py
vespa/analysis/chain_raw.py
vespa/analysis/chain_spectral.py
vespa/analysis/chain_spectral_identity.py
vespa/analysis/constants.py
vespa/analysis/deprecated_dynamic_list_user_prior.py
vespa/analysis/dialog_dataset_browser.py
vespa/analysis/dialog_experiment_indices.py
vespa/analysis/dialog_user_defined_metabolite.py
vespa/analysis/dialog_user_defined_prior.py
vespa/analysis/dialog_user_metabolite_info.py
vespa/analysis/dialog_user_prior.py
vespa/analysis/dynamic_list_giso_metabolite.py
vespa/analysis/dynamic_list_voigt_metabolite.py
vespa/analysis/figure_layouts.py
vespa/analysis/liver31p_series_sorter.py
vespa/analysis/main.py
vespa/analysis/mrs_dataset.py
vespa/analysis/mrs_macromolecule.py
Vespa_Suite-1.1.0.dist-info/LICENSE
Vespa_Suite-1.1.0.dist-info/METADATA
Vespa_Suite-1.1.0.dist-info/WHEEL
Vespa_Suite-1.1.0.dist-info/top_level.txt
Vespa_Suite-1.1.0.dist-info/RECORD
