Metadata-Version: 2.1
Name: Vespa-Suite
Version: 1.1.0
Summary: Vespa is a suite of inter-connnected applications for magnetic resonance spectroscopy simulation and data analysis.
Home-page: https://github.com/vespa-mrs/vespa/
Maintainer: Dr. Brian J. Soher
Maintainer-email: bsoher@briansoher.com
License: http://creativecommons.org/licenses/BSD/
Keywords: mri,mrs,pygamma,spectral simulation,rf pulses,magnetic resonance spectroscopy,fitting,time domain,frequency domain
Platform: Linux
Platform: OS X
Platform: Windows
Platform: POSIX
Classifier: Development Status :: 5 - Production/Stable
Classifier: Intended Audience :: Science/Research
Classifier: Intended Audience :: Healthcare Industry
Classifier: License :: OSI Approved :: BSD License
Classifier: Operating System :: MacOS :: MacOS X
Classifier: Operating System :: Unix
Classifier: Operating System :: POSIX :: Linux
Classifier: Operating System :: Microsoft :: Windows
Classifier: Programming Language :: Python :: 3.7
Requires-Dist: setuptools
